Checks/__init__.py
Checks/base.py
Checks/check_runner.py
Checks/custom_sql_check.py
Checks/null_check.py
Checks/pii_check.py
Checks/row_count_check.py
Checks/Freshness_Check/__init__.py
Checks/Freshness_Check/freshness_check.py
Checks/Freshness_Check/freshness_monitor.py
CliCheckResult/__init__.py
CliProfilerResult/__init__.py
Config_parser/Test.py
Config_parser/__init__.py
Config_parser/configService.py
Config_parser/dictHelper.py
Config_parser/nestedKeyAccessor.py
Connectors/__init__.py
Connectors/base.py
Connectors/connector_factory.py
Connectors/credential_manager.py
Connectors/rds_connector.py
Connectors/redshift_connector.py
Error/__init__.py
Error/errorHandler.py
Notification/__init__.py
Notification/notification_service.py
Profilers/__init__.py
Profilers/base_profiler.py
Profilers/column_profiler.py
Profilers/database_profiler.py
Profilers/profilingconfig.py
Profilers/table_profiler.py
Query_builder/PSQL_queries.py
Query_builder/__init__.py
Utils/__init__.py
Utils/profile_store.py
Utils/query_executor.py
Utils/sql_helpers.py
audit/__init__.py
audit/results_auditing.py
cli/__init__.py
cli/dqtoolcli.py
cli/render_check_html.py
cli/render_profiling_html.py
logger/__init__.py
logger/custom_logs.py
templates/__init__.py
templates/common/__init__.py
templates/rds/__init__.py
templates/redshift/__init__.py
dataqualitys-2.1.1.dist-info/METADATA
dataqualitys-2.1.1.dist-info/WHEEL
dataqualitys-2.1.1.dist-info/entry_points.txt
dataqualitys-2.1.1.dist-info/top_level.txt
dataqualitys-2.1.1.dist-info/RECORD
